tensorboardX/__init__.py
tensorboardX/_version.py
tensorboardX/caffe2_graph.py
tensorboardX/comet_utils.py
tensorboardX/crc32c.py
tensorboardX/embedding.py
tensorboardX/event_file_writer.py
tensorboardX/global_writer.py
tensorboardX/onnx_graph.py
tensorboardX/openvino_graph.py
tensorboardX/record_writer.py
tensorboardX/summary.py
tensorboardX/torchvis.py
tensorboardX/utils.py
tensorboardX/visdom_writer.py
tensorboardX/writer.py
tensorboardX/x2num.py
tensorboardX/beholder/__init__.py
tensorboardX/beholder/beholder.py
tensorboardX/beholder/file_system_tools.py
tensorboardX/beholder/shared_config.py
tensorboardX/beholder/video_writing.py
tensorboardX/proto/__init__.py
tensorboardX/proto/api.proto
tensorboardX/proto/api_pb2.py
tensorboardX/proto/attr_value.proto
tensorboardX/proto/attr_value_pb2.py
tensorboardX/proto/event.proto
tensorboardX/proto/event_pb2.py
tensorboardX/proto/graph.proto
tensorboardX/proto/graph_pb2.py
tensorboardX/proto/layout.proto
tensorboardX/proto/layout_pb2.py
tensorboardX/proto/node_def.proto
tensorboardX/proto/node_def_pb2.py
tensorboardX/proto/plugin_hparams.proto
tensorboardX/proto/plugin_hparams_pb2.py
tensorboardX/proto/plugin_mesh.proto
tensorboardX/proto/plugin_mesh_pb2.py
tensorboardX/proto/plugin_pr_curve.proto
tensorboardX/proto/plugin_pr_curve_pb2.py
tensorboardX/proto/plugin_text.proto
tensorboardX/proto/plugin_text_pb2.py
tensorboardX/proto/resource_handle.proto
tensorboardX/proto/resource_handle_pb2.py
tensorboardX/proto/summary.proto
tensorboardX/proto/summary_pb2.py
tensorboardX/proto/tensor.proto
tensorboardX/proto/tensor_pb2.py
tensorboardX/proto/tensor_shape.proto
tensorboardX/proto/tensor_shape_pb2.py
tensorboardX/proto/types.proto
tensorboardX/proto/types_pb2.py
tensorboardX/proto/versions.proto
tensorboardX/proto/versions_pb2.py
tensorboardX-2.6.2.1.dist-info/LICENSE
tensorboardX-2.6.2.1.dist-info/METADATA
tensorboardX-2.6.2.1.dist-info/WHEEL
tensorboardX-2.6.2.1.dist-info/top_level.txt
tensorboardX-2.6.2.1.dist-info/RECORD
