Metadata-Version: 2.1
Name: tensorboardX
Version: 2.6.2.1
Summary: TensorBoardX lets you watch Tensors Flow without Tensorflow
Home-page: https://github.com/lanpa/tensorboardX
Author: Tzu-Wei Huang
Author-email: huang.dexter@gmail.com
License: MIT license
Platform: UNKNOWN
Classifier: Development Status :: 4 - Beta
Classifier: Intended Audience :: Developers
Classifier: License :: OSI Approved :: MIT License
Classifier: Natural Language :: English
Classifier: Programming Language :: Python :: 3
Classifier: Programming Language :: Python :: 3.8
Classifier: Programming Language :: Python :: 3.9
Classifier: Programming Language :: Python :: 3.10
Classifier: Programming Language :: Python :: 3.11
License-File: LICENSE
Requires-Dist: numpy
Requires-Dist: packaging
Requires-Dist: protobuf
